MergeCRMClient/__init__.py
MergeCRMClient/api_client.py
MergeCRMClient/configuration.py
MergeCRMClient/exceptions.py
MergeCRMClient/model_utils.py
MergeCRMClient/rest.py
MergeCRMClient/api/__init__.py
MergeCRMClient/api/account_details_api.py
MergeCRMClient/api/account_token_api.py
MergeCRMClient/api/accounts_api.py
MergeCRMClient/api/available_actions_api.py
MergeCRMClient/api/contacts_api.py
MergeCRMClient/api/delete_account_api.py
MergeCRMClient/api/force_resync_api.py
MergeCRMClient/api/generate_key_api.py
MergeCRMClient/api/issues_api.py
MergeCRMClient/api/leads_api.py
MergeCRMClient/api/link_token_api.py
MergeCRMClient/api/linked_accounts_api.py
MergeCRMClient/api/notes_api.py
MergeCRMClient/api/opportunities_api.py
MergeCRMClient/api/passthrough_api.py
MergeCRMClient/api/regenerate_key_api.py
MergeCRMClient/api/stages_api.py
MergeCRMClient/api/sync_status_api.py
MergeCRMClient/api/users_api.py
MergeCRMClient/api/webhook_receivers_api.py
MergeCRMClient/apis/__init__.py
MergeCRMClient/model/__init__.py
MergeCRMClient/model/account.py
MergeCRMClient/model/account_details.py
MergeCRMClient/model/account_details_and_actions.py
MergeCRMClient/model/account_details_and_actions_integration.py
MergeCRMClient/model/account_details_and_actions_status_enum.py
MergeCRMClient/model/account_integration.py
MergeCRMClient/model/account_request.py
MergeCRMClient/model/account_token.py
MergeCRMClient/model/address.py
MergeCRMClient/model/address_request.py
MergeCRMClient/model/address_type_enum.py
MergeCRMClient/model/available_actions.py
MergeCRMClient/model/categories_enum.py
MergeCRMClient/model/category_enum.py
MergeCRMClient/model/contact.py
MergeCRMClient/model/contact_request.py
MergeCRMClient/model/country_enum.py
MergeCRMClient/model/crm_account_endpoint_request.py
MergeCRMClient/model/crm_account_response.py
MergeCRMClient/model/crm_contact_endpoint_request.py
MergeCRMClient/model/crm_contact_response.py
MergeCRMClient/model/data_passthrough_request.py
merge_crm_client-1.0.0.dist-info/LICENSE
merge_crm_client-1.0.0.dist-info/METADATA
merge_crm_client-1.0.0.dist-info/WHEEL
merge_crm_client-1.0.0.dist-info/top_level.txt
merge_crm_client-1.0.0.dist-info/RECORD
