Metadata-Version: 2.1
Name: merge-crm-client
Version: 1.0.0
Summary: Merge CRM API
Home-page: UNKNOWN
Author: Merge Team
Author-email: hello@merge.dev
License: UNKNOWN
Keywords: OpenAPI,OpenAPI-Generator,Merge CRM API
Platform: UNKNOWN
Requires-Python: >=3.6
License-File: LICENSE
Requires-Dist: urllib3 (>=1.25.3)
Requires-Dist: python-dateutil
